{"submission_id": 21076976, "title": "ARTS APPRECIATION", "filename": "files/submissions/21076976_2021-08-26_David_Lohrey__Arts_Appreciation.docx", "history": [{"date": "2021-08-26T20:12:4", "message": "None"}, {"date": "2021-08-26T20:12:4", "message": "Hi David,<br /><br />Thank you for your interest in The Decadent Review. We have received your submission and look forward to reviewing it.<br/><br />Thanks!<br />-The Decadent Review"}, {"date": "2021-08-29T11:49:0", "message": "Dear David Lohrey,<br /><br />Thank you for your submission to The Decadent Review. Although we must decline your submission this time, we appreciated the chance to consider it.<br /><br />Thanks again. Best of luck with this.<br />Sincerely,<br />Dimitri Kaufman<br />The Decadent Review<br />"}, {"date": "2021-08-29T11:50:3", "message": "None"}]}